flask_limiter_graphQL_support/__init__.py
flask_limiter_graphQL_support/_version.py
flask_limiter_graphQL_support/errors.py
flask_limiter_graphQL_support/extension.py
flask_limiter_graphQL_support/util.py
flask_limiter_graphQL_support/version.py
flask_limiter_graphQL_support/wrappers.py
Flask_Limiter_graphQL_support-0.1.5.dist-info/LICENSE.txt
Flask_Limiter_graphQL_support-0.1.5.dist-info/METADATA
Flask_Limiter_graphQL_support-0.1.5.dist-info/WHEEL
Flask_Limiter_graphQL_support-0.1.5.dist-info/top_level.txt
Flask_Limiter_graphQL_support-0.1.5.dist-info/RECORD
