Metadata-Version: 2.1
Name: Flask-Limiter-graphQL-support
Version: 0.1.5
Summary: Rate limiting for flask applications with graphQL queries and mutations support
Home-page: https://github.com/jgaye-luko/Flask-Limiter-graphQL-support
Author: Julien Gaye
Author-email: julien@getluko.com
License: MIT
Platform: UNKNOWN
Classifier: Development Status :: 5 - Production/Stable
Classifier: Environment :: Web Environment
Classifier: Intended Audience :: Developers
Classifier: License :: OSI Approved :: MIT License
Classifier: Operating System :: MacOS
Classifier: Operating System :: POSIX :: Linux
Classifier: Operating System :: OS Independent
Classifier: Topic :: Software Development :: Libraries :: Python Modules
Classifier: Programming Language :: Python :: 2.7
Classifier: Programming Language :: Python :: 3.5
Classifier: Programming Language :: Python :: Implementation :: PyPy
Requires-Dist: limits
Requires-Dist: Flask (>=0.8)
Requires-Dist: six (>=1.4.1)
